{"title":"한터차트 ─ 뮤직정보 ─ 음반신보","url":"https://www.hanteochart.com/board/newalbum","favicon":"https://www.hanteochart.com/board/favicon.ico","elements":[{"title":"현진주 - RED LIGHT","contents":"2022-07-08","retrieved":1657424055216},{"title":"한울(HANUL) - 사랑일 거야","contents":"2022-07-08","retrieved":1657424055216},{"title":"피아노의 숲 - PROLOGUE","contents":"2022-07-08","retrieved":1657424055217},{"title":"태윤 - SAGA","contents":"2022-07-08","retrieved":1657424055219},{"title":"쿨 에이드(KOOL AID) - STARLIGHT","contents":"2022-07-08","retrieved":1657424055225},{"title":"청춘스타(VA): 채널A-TV 예능, PT.8","contents":"2022-07-08","retrieved":1657424055225},{"title":"정재일 - 10.1","contents":"2022-07-08","retrieved":1657424055226},{"title":"전도을 - 그저 흔한","contents":"2022-07-08","retrieved":1657424055227},{"title":"적색밴드 - 죽택","contents":"2022-07-08","retrieved":1657424055228},{"title":"유미의 세포들 시즌2(OST): TVING 웹 드라마, PT.6","contents":"2022-07-08","retrieved":1657424055229},{"title":"위너(2, WINNER) - HOLIDAY: 미니앨범 4집, PHOTOBOOK VER.","contents":"2022-07-08","retrieved":1657424055232},{"title":"위너(2, WINNER) - HOLIDAY: 미니앨범 4집, KIT VER.","contents":"2022-07-08","retrieved":1657424055233},{"title":"위너(2, WINNER) - HOLIDAY: 미니앨범 4집, DIGIPACK VER.","contents":"2022-07-08","retrieved":1657424055234},{"title":"엠지에스(MGS) - YOU","contents":"2022-07-08","retrieved":1657424055235},{"title":"엠유엠더블유(MUMW) - MAKEUMINE","contents":"2022-07-08","retrieved":1657424055236},{"title":"에피텐드(EPTEND) - MY LIFE","contents":"2022-07-08","retrieved":1657424055237}]}