{"title":"한터차트 ─ 뮤직정보 ─ 음반신보","url":"https://www.hanteochart.com/board/newalbum","favicon":"https://www.hanteochart.com/board/favicon.ico","elements":[{"title":"탄(2, TAN) - W SERIES: 2TAN: 미니앨범 2집, WISH VER.","contents":"2022-06-21","retrieved":1655763306375},{"title":"영재(갓세븐) - SUGAR: 미니앨범 2집","contents":"2022-06-21","retrieved":1655763306378},{"title":"에스에프나인(SF9) - 3RD PHOTO BOOK, SENSUAL VER.","contents":"2022-06-21","retrieved":1655763306379},{"title":"에스에프나인(SF9) - 3RD PHOTO BOOK, NERD VER.","contents":"2022-06-21","retrieved":1655763306380},{"title":"심규선(LUCIA) - 몸과 마음, LP","contents":"2022-06-21","retrieved":1655763306382},{"title":"YOU ME AT SIX - SINNERS NEVER SLEEP: 10TH ANNI. ED.","contents":"2022-06-21","retrieved":1655763306384},{"title":"TATE MCRAE - I USED TO THINK I COULD FLY","contents":"2022-06-21","retrieved":1655763306387},{"title":"STEVE HACKETT - GENESIS REVISITED BAND&ORCHESTRA: LIVE AT THE ROYAL FESTIVAL HALL","contents":"2022-06-21","retrieved":1655763306387},{"title":"SPIDER MAN-NO WAY HOME(OST)스파이더맨-노 웨이 홈: HIGHLIGHTS","contents":"2022-06-21","retrieved":1655763306388},{"title":"ROLLING STONES - LICKED LIVE IN NYC: 2CD+DVD","contents":"2022-06-21","retrieved":1655763306390},{"title":"ROLLING STONES - LICKED LIVE IN NYC: 2CD+BLU","contents":"2022-06-21","retrieved":1655763306392},{"title":"ROLLING STONES - LICKED LIVE IN NYC","contents":"2022-06-21","retrieved":1655763306393},{"title":"ROLLING STONES - BRIDGES TO BREMEN","contents":"2022-06-21","retrieved":1655763306395},{"title":"PRINCE AND THE REVOLUTION - LIVE, TRIPLE VINYL BOX SET","contents":"2022-06-21","retrieved":1655763306396},{"title":"PRINCE AND THE REVOLUTION - LIVE, CD+BLU-RAY OVERSIZED SOFTPACK","contents":"2022-06-21","retrieved":1655763306397},{"title":"PRINCE - THE GOLD EXPERIENCE","contents":"2022-06-21","retrieved":1655763306399}]}