{"title":"한터차트 ─ 뮤직정보 ─ 음반신보","url":"https://www.hanteochart.com/board/newalbum","favicon":"https://www.hanteochart.com/board/favicon.ico","elements":[{"title":"훤(HWONS) - 그대는 그래요","contents":"2022-03-24","retrieved":1648117099705},{"title":"한림 - 추억속의 그대","contents":"2022-03-24","retrieved":1648117099706},{"title":"풀 인 더 풀(FOOL IN THE POOL) - LONELY","contents":"2022-03-24","retrieved":1648117099707},{"title":"폴 블랑코(PAUL BLANCO) - RUST","contents":"2022-03-24","retrieved":1648117099712},{"title":"톰너드(TOMNERD) - 봄비","contents":"2022-03-24","retrieved":1648117099720},{"title":"킬힐(OST): TVN-TV 수목 드라마, PT.2","contents":"2022-03-24","retrieved":1648117099722},{"title":"케네시(KENESSI) - 너","contents":"2022-03-24","retrieved":1648117099723},{"title":"지니(JINEE) - TOPSPOT","contents":"2022-03-24","retrieved":1648117099724},{"title":"지 나인(G.NINE) - STUPID","contents":"2022-03-24","retrieved":1648117099725},{"title":"조항조 - 모를 겁니다","contents":"2022-03-24","retrieved":1648117099726},{"title":"제이엠티(JMT) - STRAWBERRY","contents":"2022-03-24","retrieved":1648117099727},{"title":"이혁 - LOOP","contents":"2022-03-24","retrieved":1648117099728},{"title":"이원필 - GOD''S FLARE","contents":"2022-03-24","retrieved":1648117099730},{"title":"이석훈 1집 - 같은자리","contents":"2022-03-24","retrieved":1648117099731},{"title":"이상은 6집 - 공무도하가","contents":"2022-03-24","retrieved":1648117099732},{"title":"이상은 5집 - 언젠가는","contents":"2022-03-24","retrieved":1648117099733}]}