{"title":"한터차트 ─ 뮤직정보 ─ 음반신보","url":"https://www.hanteochart.com/board/newalbum","favicon":"https://www.hanteochart.com/board/favicon.ico","elements":[{"title":"하이라이트(HIGHLIGHT) 1집 - DAYDREAM","contents":"2022-03-21","retrieved":1647796518069},{"title":"존 노 - NSQG 2: THE OTHER SIDE","contents":"2022-03-21","retrieved":1647796518070},{"title":"양재혁(2) - AND THE COLORS","contents":"2022-03-21","retrieved":1647796518071},{"title":"레드 벨벳(2, RED VELVET) - THE REVE FESTIVAL 2022: FEEL MY RHYTHM, REVE VER.","contents":"2022-03-21","retrieved":1647796518072},{"title":"레드 벨벳(2, RED VELVET) - THE REVE FESTIVAL 2022: FEEL MY RHYTHM, ORGEL VER.","contents":"2022-03-21","retrieved":1647796518076},{"title":"희상 - 달","contents":"2022-03-18","retrieved":1647796518077},{"title":"홈스윗뮤직 - MOONLIGHT","contents":"2022-03-18","retrieved":1647796518078},{"title":"해든(코어 로우) - HEARTLESS","contents":"2022-03-18","retrieved":1647796518083},{"title":"필윤(PHIL YOON) - SEAGULL & DRONE","contents":"2022-03-18","retrieved":1647796518083},{"title":"펄키드(PXARX KID) - NOBODY","contents":"2022-03-18","retrieved":1647796518084},{"title":"트레이서(OST): MBC-TV 금토 드라마","contents":"2022-03-18","retrieved":1647796518085},{"title":"키드 킹(KIDD KING) - EMOTIONAL BAGGAGE","contents":"2022-03-18","retrieved":1647796518087},{"title":"카라신주니어(KARACIN JR.)/나오(NA0H) - PINK PARAD0X","contents":"2022-03-18","retrieved":1647796518088},{"title":"조현아 - 늦은 후회","contents":"2022-03-18","retrieved":1647796518089},{"title":"조인호 - WATER","contents":"2022-03-18","retrieved":1647796518090},{"title":"정상수 - 환상의 명사수: 웹툰 나쁜 녀석들(OST)","contents":"2022-03-18","retrieved":1647796518091}]}