{"title":"한터차트 ─ 뮤직정보 ─ 발매일정","url":"https://www.hanteochart.com/board/schedule","favicon":"https://www.hanteochart.com/board/favicon.ico","elements":[{"title":"유희열 - 생활음악 LP","contents":"9999-12-31","retrieved":1655742374068},{"title":"수호(엑소) - GREY SUIT: 미니앨범 2집, LP VER.","contents":"2023-01-25","retrieved":1655742374068},{"title":"스물다섯 스물하나(OST): TVN-TV 주말 드라마, LP","contents":"2022-12-14","retrieved":1655742374068},{"title":"프로듀사(OST): KBS-2TV 드라마, LP","contents":"2022-12-01","retrieved":1655742374068},{"title":"태연 3집 - INVU, LP VER.","contents":"2022-12-01","retrieved":1655742374072},{"title":"업타운(UPTOWN) 1집 - REPRESENT, LP","contents":"2022-12-01","retrieved":1655742374072},{"title":"어쩌다 발견한 하루(OST): MBC-TV 수목 드라마, LP","contents":"2022-12-01","retrieved":1655742374074},{"title":"스타트업(OST): TVN-TV 주말 드라마, LP","contents":"2022-12-01","retrieved":1655742374075},{"title":"하현상 - CALIBRATE: 미니앨범 3집, REMASTERED LP","contents":"2022-11-30","retrieved":1655742374076},{"title":"설강화(OST): JTBC-TV 주말 드라마, LP","contents":"2022-11-21","retrieved":1655742374077},{"title":"폴킴(PAUL KIM) - PKALBUM, ECO EDITION","contents":"2022-10-31","retrieved":1655742374078},{"title":"폴킴(PAUL KIM) - PKALBUM","contents":"2022-10-31","retrieved":1655742374080},{"title":"신용재 - 사계, LIMITED ED.","contents":"2022-10-27","retrieved":1655742374081},{"title":"소울바이서울(SOULBYSEL) - SOULBYSEL COMPILATION 01","contents":"2022-10-26","retrieved":1655742374082},{"title":"에덴의 동쪽(OST): MBC-TV 창사 47주년 특별기획 드라마, LP","contents":"2022-10-06","retrieved":1655742374084},{"title":"슬픔보다 더 슬픈 이야기(OST), LP","contents":"2022-10-06","retrieved":1655742374086}]}